peppy/__init__.py
peppy/_version.py
peppy/const.py
peppy/exceptions.py
peppy/parsers.py
peppy/project.py
peppy/sample.py
peppy/simple_attr_map.py
peppy/utils.py
peppy-0.40.6.dist-info/LICENSE.txt
peppy-0.40.6.dist-info/METADATA
peppy-0.40.6.dist-info/WHEEL
peppy-0.40.6.dist-info/top_level.txt
peppy-0.40.6.dist-info/RECORD
