Metadata-Version: 2.1
Name: peppy
Version: 0.40.6
Summary: A python-based project metadata manager for portable encapsulated projects
Home-page: https://github.com/pepkit/peppy/
Author: Michal Stolarczyk, Nathan Sheffield, Vince Reuter, Andre Rendeiro, Oleksandr Khoroshevskyi
License: BSD2
Keywords: project,metadata,bioinformatics,sequencing,ngs,workflow
Classifier: Development Status :: 4 - Beta
Classifier: License :: OSI Approved :: BSD License
Classifier: Programming Language :: Python :: 3.8
Classifier: Programming Language :: Python :: 3.9
Classifier: Programming Language :: Python :: 3.10
Classifier: Programming Language :: Python :: 3.11
Classifier: Programming Language :: Python :: 3.12
Classifier: Topic :: Scientific/Engineering :: Bio-Informatics
License-File: LICENSE.txt
Requires-Dist: pandas>=0.24.2
Requires-Dist: pyyaml
Requires-Dist: rich>=10.3.0
Requires-Dist: ubiquerg>=0.6.2
Requires-Dist: numpy
Requires-Dist: pephubclient>=0.4.2
